ebuilder/__init__.py
ebuilder/ebuilder_core.py
ebuilder/ebuilder_decorators.py
Ebuilder-0.2.6.3.2.dist-info/LICENSE
Ebuilder-0.2.6.3.2.dist-info/METADATA
Ebuilder-0.2.6.3.2.dist-info/WHEEL
Ebuilder-0.2.6.3.2.dist-info/top_level.txt
Ebuilder-0.2.6.3.2.dist-info/RECORD
